bottle_suite/__init__.py
bottle_suite/bottle_suite.py
bottle_suite/reload.py
bottle_suite/resource_factory.py
bottle_suite/resources.py
bottle_suite/dashboard/__init__.py
bottle_suite/dashboard/dist/.nojekyll
bottle_suite/dashboard/dist/200.html
bottle_suite/dashboard/dist/favicon.ico
bottle_suite/dashboard/dist/index.html
bottle_suite/dashboard/dist/_nuxt/10fdf79.js
bottle_suite/dashboard/dist/_nuxt/1ac7e5a.js
bottle_suite/dashboard/dist/_nuxt/22c058d.js
bottle_suite/dashboard/dist/_nuxt/36aef69.js
bottle_suite/dashboard/dist/_nuxt/472182f.js
bottle_suite/dashboard/dist/_nuxt/648aaa9.js
bottle_suite/dashboard/dist/_nuxt/70cc831.js
bottle_suite/dashboard/dist/_nuxt/9be4c3d.js
bottle_suite/dashboard/dist/_nuxt/LICENSES
bottle_suite/dashboard/dist/_nuxt/ca0c209.js
bottle_suite/dashboard/dist/_nuxt/ca5237f.js
bottle_suite/dashboard/dist/_nuxt/cc1e9bf.js
bottle_suite/dashboard/dist/_nuxt/ef3c73c.js
bottle_suite/dashboard/dist/_nuxt/f554c1e.js
bottle_suite/dashboard/dist/config/index.html
bottle_suite/dashboard/dist/login/index.html
bottle_suite/dashboard/dist/resources/index.html
bottle_suite/dashboard/resources/__init__.py
bottle_suite/dashboard/resources/token.py
scripts/app.py
scripts/create.py
scripts/hello_world.py
bottle_suite-0.0.17.dist-info/LICENSE
bottle_suite-0.0.17.dist-info/METADATA
bottle_suite-0.0.17.dist-info/WHEEL
bottle_suite-0.0.17.dist-info/entry_points.txt
bottle_suite-0.0.17.dist-info/top_level.txt
bottle_suite-0.0.17.dist-info/RECORD
