Metadata-Version: 2.1
Name: bottle-suite
Version: 0.0.17
Summary: bottle.py suite with CORS, SQL, REST, and JWT
Author-email: TJ Renninger <renninger12@gmail.com>
Classifier: Programming Language :: Python :: 3
Classifier: License :: OSI Approved :: MIT License
Classifier: Operating System :: OS Independent
Requires-Python: >=3.8
License-File: LICENSE
Requires-Dist: bottle-restful >=0.0.1
Requires-Dist: bottle-jwt3 >=0.0.1
Requires-Dist: bottle-sql >=0.0.1
Requires-Dist: bottle-cors2 >=0.0.1
Requires-Dist: toml >=0.10.2
